pycamera/__init__.py
pycamera/camera.py
pycamera/frame.py
pycamera-0.3.2.dist-info/LICENSE
pycamera-0.3.2.dist-info/METADATA
pycamera-0.3.2.dist-info/WHEEL
pycamera-0.3.2.dist-info/top_level.txt
pycamera-0.3.2.dist-info/RECORD
