Metadata-Version: 2.1
Name: pycamera
Version: 0.3.2
Summary: An easier solution to computer vision.
Home-page: https://github.com/IsmaeelAkram/pycamera
Author: Ismaeel Akram
License: MIT
Platform: UNKNOWN
Requires-Python: >=3.4.0
License-File: LICENSE
